README.rst
setup.cfg
setup.py
mattoolkit/__init__.py
mattoolkit/__main__.py
mattoolkit/logging.py
mattoolkit.egg-info/PKG-INFO
mattoolkit.egg-info/SOURCES.txt
mattoolkit.egg-info/dependency_links.txt
mattoolkit.egg-info/entry_points.txt
mattoolkit.egg-info/requires.txt
mattoolkit.egg-info/top_level.txt
mattoolkit/api/__init__.py
mattoolkit/api/api.py
mattoolkit/api/calculation.py
mattoolkit/api/cluster.py
mattoolkit/api/resource.py
mattoolkit/api/structure.py
mattoolkit/api/user.py
mattoolkit/cli/__init__.py
mattoolkit/cli/api.py
mattoolkit/cli/auth.py
mattoolkit/cli/job.py
mattoolkit/cli/template.py
mattoolkit/jobs/__init__.py
mattoolkit/jobs/base.py
mattoolkit/jobs/run.py
mattoolkit/jobs/software/__init__.py
mattoolkit/jobs/software/vasp.py
mattoolkit/jobs/transformation/__init__.py
mattoolkit/jobs/transformation/additions.py
mattoolkit/tasks/__init__.py
mattoolkit/tasks/config.py
mattoolkit/tasks/elastic.py
mattoolkit/tasks/general.py
mattoolkit/tasks/vasp.py
mattoolkit/tasks/calculation/__init__.py
mattoolkit/tasks/calculation/espresso.py
mattoolkit/tasks/calculation/vasp.py
mattoolkit/tasks/structure/__init__.py
mattoolkit/tasks/structure/pmg.py
mattoolkit/template/__init__.py
mattoolkit/template/parse.py
mattoolkit/template/representation/__init__.py
mattoolkit/template/representation/base.py
mattoolkit/template/representation/calculation.py
mattoolkit/template/representation/cluster.py
mattoolkit/template/representation/structure.py
mattoolkit/template/representation/transformation.py
mattoolkit/template/representation/user.py
mattoolkit/template/representation/software/__init__.py
mattoolkit/template/representation/software/vasp.py
mattoolkit/template/schema/__init__.py
mattoolkit/template/schema/base.py
mattoolkit/template/schema/calculation.py
mattoolkit/template/schema/cluster.py
mattoolkit/template/schema/fields.py
mattoolkit/template/schema/structure.py
mattoolkit/template/schema/transformation.py
mattoolkit/template/schema/user.py
mattoolkit/template/schema/software/__init__.py
mattoolkit/template/schema/software/vasp.py
tests/jobs/__init__.py
tests/jobs/test_lammps.py
tests/jobs/test_vasp.py
tests/templates/__init__.py
