Metadata-Version: 1.1
Name: mattoolkit
Version: 0.0.30
Summary: Material Toolkit cli and library
Home-page: https://gitlab.aves.io/mattoolkit/mattoolkit-client
Author: Chris Ostrouchov
Author-email: chris.ostrouchov+mtk-cli@gmail.com
License: UNKNOWN
Download-URL: https://gitlab.aves.io/mattoolkit/mattoolkit-client/repository/archive.zip?ref=v0.0.30
Keywords: material toolkit material science hpc vasp
Platform: UNKNOWN
Classifier: Programming Language :: Python :: 3.5
Classifier: Programming Language :: Python :: 3.6
